config/.gitignore
config/__init__.py
config/_version.py
config/configuration.py
config/configuration_set.py
config/helpers.py
config/py.typed
config/contrib/__init__.py
config/contrib/aws.py
config/contrib/azure.py
config/contrib/gcp.py
config/contrib/vault.py
python_configuration-0.12.1.dist-info/METADATA
python_configuration-0.12.1.dist-info/WHEEL
python_configuration-0.12.1.dist-info/licenses/LICENSE
python_configuration-0.12.1.dist-info/RECORD
