Metadata-Version: 2.3
Name: python-configuration
Version: 0.12.1
Summary: A library to load configuration parameters from multiple sources and formats
Project-URL: Homepage, https://tr11.github.io/python-configuration/
Project-URL: Documentation, https://tr11.github.io/python-configuration/
Project-URL: Issues, https://github.com/tr11/python-configuration/issues
Project-URL: Source, https://github.com/tr11/python-configuration
Author-email: Tiago Requeijo <tiago.requeijo.dev@gmail.com>
License: MIT
License-File: LICENSE
Keywords: configuration,ini,json,settings,toml,yaml
Classifier: Programming Language :: Python
Classifier: Programming Language :: Python :: 3.8
Classifier: Programming Language :: Python :: 3.9
Classifier: Programming Language :: Python :: 3.10
Classifier: Programming Language :: Python :: 3.11
Classifier: Programming Language :: Python :: 3.12
Classifier: Programming Language :: Python :: Implementation :: CPython
Classifier: Programming Language :: Python :: Implementation :: PyPy
Requires-Python: >=3.8
Provides-Extra: aws
Requires-Dist: boto3>=1.28.20; extra == 'aws'
Provides-Extra: azure
Requires-Dist: azure-identity; extra == 'azure'
Requires-Dist: azure-keyvault>=4.2.0; extra == 'azure'
Provides-Extra: cloud
Requires-Dist: azure-identity; extra == 'cloud'
Requires-Dist: azure-keyvault>=4.2.0; extra == 'cloud'
Requires-Dist: boto3>=1.28.20; extra == 'cloud'
Requires-Dist: google-cloud-secret-manager>=2.16.3; extra == 'cloud'
Requires-Dist: hvac>=1.1.1; extra == 'cloud'
Provides-Extra: file-formats
Requires-Dist: pyyaml>=6.0; extra == 'file-formats'
Requires-Dist: tomli>=2.0.1; extra == 'file-formats'
Provides-Extra: gcp
Requires-Dist: google-cloud-secret-manager>=2.16.3; extra == 'gcp'
Provides-Extra: toml
Requires-Dist: tomli>=2.0.1; extra == 'toml'
Provides-Extra: validation
Requires-Dist: jsonschema>=4.21.1; extra == 'validation'
Provides-Extra: vault
Requires-Dist: hvac>=1.1.1; extra == 'vault'
Provides-Extra: yaml
Requires-Dist: pyyaml>=6.0; extra == 'yaml'
